simple_build/README.md
simple_build/__init__.py
simple_build/analyse/__init__.py
simple_build/analyse/_analyse.py
simple_build/analyse/_pep621.py
simple_build/analyse/_pyproject.py
simple_build/backend.py
simple_build/build.py
simple_build/py.typed
simple_build/write/__init__.py
simple_build/write/_files.py
simple_build/write/_git.py
simple_build/write/_metadata.py
simple_build/write/_sdist.py
simple_build/write/_wheel.py
simple_build-0.0.3.dist-info/licenses/LICENSE
simple_build-0.0.3.dist-info/WHEEL
simple_build-0.0.3.dist-info/METADATA
simple_build-0.0.3.dist-info/RECORD
