Metadata-Version: 2.1
Name: simple-build
Version: 0.0.3
Summary: A simple build-backend for Python.
Author-email: Chris Sewell <chrisj_sewell@hotmail.com>
Project-URL: Code, https://github.com/chrisjsewell/simple-build
Classifier: Development Status :: 3 - Alpha
Classifier: Intended Audience :: Developers
Classifier: License :: OSI Approved :: MIT License
Classifier: Operating System :: OS Independent
Classifier: Programming Language :: Python :: 3
Requires-Python: >=3.11
Requires-Dist: packaging>=22
